rr_block/__init__.py
rr_block/rr_layer.py
rr_block-0.1.2.dist-info/METADATA
rr_block-0.1.2.dist-info/WHEEL
rr_block-0.1.2.dist-info/top_level.txt
rr_block-0.1.2.dist-info/RECORD
