Metadata-Version: 2.4
Name: rr-block
Version: 0.1.2
Summary: The remix and reactivate (RR) Block for PyTorch
Author-email: Anonymous <u2ido6jir@mozmail.com>
License: MIT
Project-URL: Homepage, https://github.com/
Project-URL: Repository, https://github.com/
Classifier: Development Status :: 4 - Beta
Classifier: Environment :: GPU :: NVIDIA CUDA
Classifier: Intended Audience :: Developers
Classifier: Intended Audience :: Science/Research
Classifier: License :: OSI Approved :: MIT License
Classifier: Operating System :: OS Independent
Classifier: Programming Language :: Python :: 3
Classifier: Programming Language :: Python :: 3.10
Classifier: Programming Language :: Python :: 3.11
Classifier: Programming Language :: Python :: 3.12
Classifier: Topic :: Scientific/Engineering :: Artificial Intelligence
Classifier: Topic :: Software Development :: Libraries :: Python Modules
Classifier: Typing :: Typed
Requires-Python: >=3.8
Requires-Dist: torch>=1.8
Provides-Extra: dev
Requires-Dist: pytest>=8.0; extra == "dev"
Requires-Dist: build; extra == "dev"
Requires-Dist: twine; extra == "dev"
